aircraft_models/__init__.py
aircraft_models/aircraft_list.py
aircraft_models-1.1.dist-info/LICENSE
aircraft_models-1.1.dist-info/METADATA
aircraft_models-1.1.dist-info/WHEEL
aircraft_models-1.1.dist-info/top_level.txt
aircraft_models-1.1.dist-info/RECORD
